expression/__init__.py
expression/_version.py
expression/collections/__init__.py
expression/collections/array.py
expression/collections/asyncseq.py
expression/collections/block.py
expression/collections/map.py
expression/collections/maptree.py
expression/collections/seq.py
expression/core/__init__.py
expression/core/aiotools.py
expression/core/builder.py
expression/core/compose.py
expression/core/curry.py
expression/core/error.py
expression/core/fn.py
expression/core/mailbox.py
expression/core/misc.py
expression/core/option.py
expression/core/pipe.py
expression/core/result.py
expression/core/tagged_union.py
expression/core/try_.py
expression/core/typing.py
expression/effect/__init__.py
expression/effect/option.py
expression/effect/result.py
expression/effect/seq.py
expression/extra/__init__.py
expression/extra/option/__init__.py
expression/extra/option/pipeline.py
expression/extra/parser.py
expression/extra/result/__init__.py
expression/extra/result/catch.py
expression/extra/result/pipeline.py
expression/extra/result/traversable.py
expression/py.typed
expression/system/__init__.py
expression/system/cancellation.py
expression/system/disposable.py
expression/system/error.py
expression-5.5.0.dist-info/LICENSE
expression-5.5.0.dist-info/METADATA
expression-5.5.0.dist-info/WHEEL
expression-5.5.0.dist-info/RECORD
