Metadata-Version: 2.3
Name: Expression
Version: 5.5.0
Summary: Practical functional programming for Python 3.10+
Home-page: https://github.com/cognitedata/Expression
License: MIT
Author: Dag Brattli
Author-email: dag.brattli@cognite.com
Requires-Python: >=3.10,<4
Classifier: Development Status :: 5 - Production/Stable
Classifier: Environment :: Other Environment
Classifier: Intended Audience :: Developers
Classifier: License :: OSI Approved :: MIT License
Classifier: Operating System :: OS Independent
Classifier: Programming Language :: Python :: 3
Classifier: Programming Language :: Python :: 3.10
Classifier: Programming Language :: Python :: 3.11
Classifier: Programming Language :: Python :: 3.12
Classifier: Programming Language :: Python :: 3.13
Classifier: Programming Language :: Python :: Implementation :: CPython
Classifier: Topic :: Software Development :: Libraries :: Python Modules
Provides-Extra: all
Provides-Extra: pydantic
Requires-Dist: pydantic (>=2.6.2,<3.0.0) ; extra == "pydantic" or extra == "all"
Requires-Dist: typing-extensions (>=4.6.0)
